Analysis/SentimentAnalysis.py
Analysis/__init__.py
Analysis/SentimentModels/NLTK.py
Analysis/SentimentModels/__init__.py
SMD_Analysis-1.1.dist-info/METADATA
SMD_Analysis-1.1.dist-info/RECORD
SMD_Analysis-1.1.dist-info/WHEEL
SMD_Analysis-1.1.dist-info/top_level.txt
