Metadata-Version: 2.1
Name: SMD-Analysis
Version: 1.1
Summary: An API for social media data analysis
Home-page: UNKNOWN
Author: rehab shahzadi
Author-email: rehab.shahzadi@kics.edu.pk
License: UNKNOWN
Platform: UNKNOWN
Classifier: Programming Language :: Python :: 3
Classifier: Operating System :: OS Independent
Requires-Dist: pandas (==0.23.4)
Requires-Dist: nltk (==3.3)
Requires-Dist: scikit-learn (==0.19.2)
Requires-Dist: scipy (==1.1.0)
